{
"nodes":[
	{ "name": "韩菱纱"   , "image" : "https://timgsa.baidu.com/timg?image&quality=80&size=b9999_10000&sec=1528777758417&di=c32280b28e9867c0bf1846117fea5596&imgtype=0&src=http%3A%2F%2Fi1.hdslb.com%2Fbfs%2Farchive%2F96dce37d84f4c86595b6ad2f5b31f2547e7a6f06.jpg" },
	{ "name": "云天河"   , "image" : "https://timgsa.baidu.com/timg?image&quality=80&size=b9999_10000&sec=1528777758417&di=c32280b28e9867c0bf1846117fea5596&imgtype=0&src=http%3A%2F%2Fi1.hdslb.com%2Fbfs%2Farchive%2F96dce37d84f4c86595b6ad2f5b31f2547e7a6f06.jpg" },
	{ "name": "柳梦璃"   , "image" : "https://timgsa.baidu.com/timg?image&quality=80&size=b9999_10000&sec=1528777758417&di=c32280b28e9867c0bf1846117fea5596&imgtype=0&src=http%3A%2F%2Fi1.hdslb.com%2Fbfs%2Farchive%2F96dce37d84f4c86595b6ad2f5b31f2547e7a6f06.jpg" }
],
"edges":[
	{ "source": 0 , "target": 1 , "relation":"同学" ,"url": "http://www.baidu.com"},
	{ "source": 0 , "target": 2 , "relation":"挚友" ,"url": "http://www.baidu.com"},
	{ "source": 1 , "target": 2 , "relation":"恋人" ,"url": "http://www.baidu.com"}
]
}